leuci_xyz/__init__.py
leuci_xyz/axestransform.py
leuci_xyz/crstransform.py
leuci_xyz/gridmaker.py
leuci_xyz/matrix3d.py
leuci_xyz/matrixthree.py
leuci_xyz/matrixthreex.py
leuci_xyz/matrixthreey.py
leuci_xyz/spacetransform.py
leuci_xyz/vectorthree.py
leuci_xyz-0.0.26.dist-info/METADATA
leuci_xyz-0.0.26.dist-info/WHEEL
leuci_xyz-0.0.26.dist-info/top_level.txt
leuci_xyz-0.0.26.dist-info/RECORD
